{
    "target_repo": {
        "url": "https://github.com/MicrosoftDocs/azure-docs-sdk-node",
        "branch": "smoke-test-legacy",
        "folder": "previous-packages"
    },
    "npm_package_sources": [
        {
            "name": "@azure/storage-blob@10.5.0"
        },
        {
            "name": "@azure/storage-queue@10.3.0"
        },
        {
            "name": "azure-arm-storageimportexport"
        },
        {
            "name": "azure-arm-storage"
        },
        {
            "name": "azure-keyvault"
        },
        {
            "name": "azure-arm-keyvault"
        },
        {
            "name": "@azure/storage-file@10.3.0"
        },
        {
            "name": "@azure/event-hubs@2.1.4"
        },
        {
            "name": "azure-storage",
            "folder": "./typings/azure-storage"
        },
        {
            "name": "azure-arm-eventhub"
        },
        {
            "name": "azure-arm-analysisservices"
        },
        {
            "name": "azure-arm-apimanagement"
        },
        {
            "name": "azure-arm-appinsights"
        },
        {
            "name": "azure-arm-automation@9.1.0-preview"
        },
        {
            "name": "azure-arm-azurestack@1.1.0-preview"
        },
        {
            "name": "azure-arm-commerce"
        },
        {
            "name": "azure-arm-compute"
        },
        {
            "name": "azure-arm-containerservice"
        },
        {
            "name": "azure-arm-cosmosdb"
        },
        {
            "name": "azure-arm-customerinsights"
        },
        {
            "name": "azure-arm-databox"
        },
        {
            "name": "azure-arm-databox@2.1.0-preview"
        },
        {
            "name": "azure-arm-databricks"
        },
        {
            "name": "azure-arm-datacatalog"
        },
        {
            "name": "azure-arm-datafactory"
        },
        {
            "name": "azure-arm-deploymentmanager"
        },
        {
            "name": "azure-arm-deploymentmanager@2.1.0-preview"
        },
        {
            "name": "azure-arm-deviceprovisioningservices"
        },
        {
            "name": "azure-arm-devspaces"
        },
        {
            "name": "azure-arm-devtestlabs"
        },
        {
            "name": "azure-arm-dns"
        },
        {
            "name": "azure-arm-domainservices"
        },
        {
            "name": "azure-arm-eventgrid"
        },
        {
            "name": "azure-arm-eventhub"
        },
        {
            "name": "azure-arm-frontdoor"
        },
        {
            "name": "azure-arm-frontdoor@3.1.0-preview"
        },
        {
            "name": "azure-arm-hanaonazure"
        },
        {
            "name": "azure-arm-hdinsight"
        },
        {
            "name": "azure-arm-iotcentral"
        },
        {
            "name": "azure-arm-iothub"
        },
        {
            "name": "azure-arm-iotspaces"
        },
        {
            "name": "azure-arm-iotspaces@1.1.0-preview"
        },
        {
            "name": "azure-arm-keyvault"
        },
        {
            "name": "azure-arm-kusto"
        },
        {
            "name": "azure-arm-labservices"
        },
        {
            "name": "azure-arm-locationbasedservices"
        },
        {
            "name": "azure-arm-logic"
        },
        {
            "name": "azure-arm-machinelearningcompute"
        },
        {
            "name": "azure-arm-machinelearningcompute@1.1.0-preview"
        },
        {
            "name": "azure-arm-machinelearningexperimentation"
        },
        {
            "name": "azure-arm-machinelearningexperimentation@1.1.0-preview"
        },
        {
            "name": "azure-arm-machinelearningservices"
        },
        {
            "name": "azure-arm-machinelearningservices@2.1.0-preview"
        },
        {
            "name": "azure-arm-managementgroups"
        },
        {
            "name": "azure-arm-managementpartner"
        },
        {
            "name": "azure-arm-managementpartner@1.1.0-preview"
        },
        {
            "name": "azure-arm-maps"
        },
        {
            "name": "azure-arm-mariadb"
        },
        {
            "name": "azure-arm-marketplaceordering"
        },
        {
            "name": "azure-arm-mediaservices"
        },
        {
            "name": "azure-arm-migrate"
        },
        {
            "name": "azure-arm-monitor"
        },
        {
            "name": "azure-arm-msi"
        },
        {
            "name": "azure-arm-msi@1.1.0-preview"
        },
        {
            "name": "azure-arm-mysql"
        },
        {
            "name": "azure-arm-network"
        },
        {
            "name": "azure-arm-notificationhubs"
        },
        {
            "name": "azure-arm-operationalinsights"
        },
        {
            "name": "azure-arm-operations"
        },
        {
            "name": "azure-arm-operations@2.1.0-preview"
        },
        {
            "name": "azure-arm-policyinsights"
        },
        {
            "name": "azure-arm-postgresql"
        },
        {
            "name": "azure-arm-powerbidedicated"
        },
        {
            "name": "azure-arm-powerbidedicated@1.1.0-preview"
        },
        {
            "name": "azure-arm-powerbiembedded@1.2.0-preview"
        },
        {
            "name": "azure-arm-recoveryservices"
        },
        {
            "name": "azure-arm-recoveryservices-siterecovery"
        },
        {
            "name": "azure-arm-recoveryservicesbackup"
        },
        {
            "name": "azure-arm-rediscache"
        },
        {
            "name": "azure-arm-relay"
        },
        {
            "name": "azure-arm-relay@2.1.0-preview"
        },
        {
            "name": "azure-arm-reservations"
        },
        {
            "name": "azure-arm-resource"
        },
        {
            "name": "azure-arm-resourcehealth"
        },
        {
            "name": "azure-arm-sb"
        },
        {
            "name": "azure-arm-search"
        },
        {
            "name": "azure-arm-security"
        },
        {
            "name": "azure-arm-security@1.2.0-preview"
        },
        {
            "name": "azure-arm-servicefabric"
        },
        {
            "name": "azure-arm-servicefabric@2.1.0-preview"
        },
        {
            "name": "azure-arm-servicefabricmesh"
        },
        {
            "name": "azure-arm-servicefabricmesh@2.1.0-preview"
        },
        {
            "name": "azure-arm-servicemap"
        },
        {
            "name": "azure-arm-signalr"
        },
        {
            "name": "azure-arm-signalr@1.2.0-preview"
        },
        {
            "name": "azure-arm-sql"
        },
        {
            "name": "azure-arm-sqlvirtualmachine"
        },
        {
            "name": "azure-arm-storage"
        },
        {
            "name": "azure-arm-storageimportexport"
        },
        {
            "name": "azure-arm-storagesync"
        },
        {
            "name": "azure-arm-storsimple1200series"
        },
        {
            "name": "azure-arm-storsimple8000series@1.1.0-preview"
        },
        {
            "name": "azure-arm-streamanalytics"
        },
        {
            "name": "azure-arm-streamanalytics@1.1.0-preview"
        },
        {
            "name": "azure-arm-subscription"
        },
        {
            "name": "azure-arm-subscription@1.0.0-preview"
        },
        {
            "name": "azure-arm-timeseriesinsights"
        },
        {
            "name": "azure-arm-trafficmanager"
        },
        {
            "name": "azure-arm-visualstudio"
        },
        {
            "name": "azure-arm-visualstudio@2.2.0-preview"
        },
        {
            "name": "azure-arm-website"
        },
        {
            "name": "azure-asm-hdinsight"
        },
        {
            "name": "azure-asm-network"
        },
        {
            "name": "azure-asm-sb"
        },
        {
            "name": "azure-asm-scheduler"
        },
        {
            "name": "azure-asm-sql"
        },
        {
            "name": "azure-asm-storage"
        },
        {
            "name": "azure-asm-store"
        },
        {
            "name": "azure-asm-subscription"
        },
        {
            "name": "azure-asm-trafficmanager"
        },
        {
            "name": "azure-asm-website"
        },
        {
            "name": "azure-eventgrid"
        },
        {
            "name": "azure-graph"
        },
        {
            "name": "azure-monitoring"
        },
        {
            "name": "azure-scheduler"
        },
        {
            "name": "azure-servicefabric"
        }
    ]
}