{
  "Name": "@azure/communication-phone-numbers",
  "Version": "1.5.0",
  "DevVersion": null,
  "DirectoryPath": "sdk/communication/communication-phone-numbers",
  "ServiceDirectory": "communication",
  "ReadMePath": "sdk/communication/communication-phone-numbers/README.md",
  "ChangeLogPath": "sdk/communication/communication-phone-numbers/CHANGELOG.md",
  "Group": null,
  "SdkType": "client",
  "IsNewSdk": true,
  "ArtifactName": "azure-communication-phone-numbers",
  "ReleaseStatus": "2025-08-28",
  "IncludedForValidation": false,
  "AdditionalValidationPackages": null,
  "ArtifactDetails": {
    "triggeringPaths": [
      "/sdk/communication/ci.yml"
    ],
    "safeName": "azurecommunicationphonenumbers",
    "name": "azure-communication-phone-numbers"
  },
  "CIParameters": {
    "CIMatrixConfigs": []
  },
  "CIMatrixConfigs": []
}
