{
  "Name": "@azure/cosmos",
  "Version": "4.5.0",
  "DevVersion": null,
  "DirectoryPath": "sdk/cosmosdb/cosmos",
  "ServiceDirectory": "cosmosdb",
  "ReadMePath": "sdk/cosmosdb/cosmos/README.md",
  "ChangeLogPath": "sdk/cosmosdb/cosmos/CHANGELOG.md",
  "Group": null,
  "SdkType": "client",
  "IsNewSdk": true,
  "ArtifactName": "azure-cosmos",
  "ReleaseStatus": "2025-07-21",
  "IncludedForValidation": false,
  "AdditionalValidationPackages": null,
  "ArtifactDetails": {
    "triggeringPaths": [
      "/sdk/cosmosdb/ci.yml"
    ],
    "name": "azure-cosmos",
    "safeName": "azurecosmos"
  },
  "CIParameters": {
    "CIMatrixConfigs": []
  },
  "CIMatrixConfigs": [],
  "DependentPackages": null
}
