{
  "Name": "@azure/playwright",
  "Version": "1.1.0",
  "DevVersion": null,
  "DirectoryPath": "sdk/loadtesting/playwright",
  "ServiceDirectory": "loadtesting",
  "ReadMePath": "sdk/loadtesting/playwright/README.md",
  "ChangeLogPath": "sdk/loadtesting/playwright/CHANGELOG.md",
  "Group": null,
  "SdkType": "client",
  "IsNewSdk": true,
  "ArtifactName": "azure-playwright",
  "ReleaseStatus": "2026-01-06",
  "IncludedForValidation": false,
  "AdditionalValidationPackages": null,
  "ArtifactDetails": {
    "name": "azure-playwright",
    "safeName": "azureplaywright",
    "triggeringPaths": [
      "/sdk/loadtesting/ci.yml"
    ]
  },
  "CIParameters": {
    "CIMatrixConfigs": []
  },
  "SpecProjectPath": null
}
