{
  "Name": "@azure/arm-cdn",
  "Version": "9.1.2-alpha.20260217.1",
  "DevVersion": "9.1.2-alpha.20260217.1",
  "DirectoryPath": "sdk/cdn/arm-cdn",
  "ServiceDirectory": "cdn",
  "ReadMePath": "sdk/cdn/arm-cdn/README.md",
  "ChangeLogPath": "sdk/cdn/arm-cdn/CHANGELOG.md",
  "Group": null,
  "SdkType": "mgmt",
  "IsNewSdk": true,
  "ArtifactName": "azure-arm-cdn",
  "ReleaseStatus": "Unreleased",
  "IncludedForValidation": false,
  "AdditionalValidationPackages": null,
  "ArtifactDetails": {
    "safeName": "azurearmcdn",
    "name": "azure-arm-cdn",
    "triggeringPaths": [
      "/sdk/cdn/ci.mgmt.yml"
    ]
  },
  "CIParameters": {
    "CIMatrixConfigs": []
  },
  "SpecProjectPath": null
}
