{
  "Name": "@azure/arm-operationalinsights",
  "Version": "10.0.0-alpha.20251231.1",
  "DevVersion": "10.0.0-alpha.20251231.1",
  "DirectoryPath": "sdk/operationalinsights/arm-operationalinsights",
  "ServiceDirectory": "operationalinsights",
  "ReadMePath": "sdk/operationalinsights/arm-operationalinsights/README.md",
  "ChangeLogPath": "sdk/operationalinsights/arm-operationalinsights/CHANGELOG.md",
  "Group": null,
  "SdkType": "mgmt",
  "IsNewSdk": true,
  "ArtifactName": "azure-arm-operationalinsights",
  "ReleaseStatus": "2025-12-15",
  "IncludedForValidation": false,
  "AdditionalValidationPackages": null,
  "ArtifactDetails": {
    "safeName": "azurearmoperationalinsights",
    "name": "azure-arm-operationalinsights",
    "triggeringPaths": [
      "/sdk/operationalinsights/ci.mgmt.yml"
    ]
  },
  "CIParameters": {
    "CIMatrixConfigs": []
  },
  "SpecProjectPath": null
}
