{
  "Name": "@azure/arm-storagesync",
  "Version": "9.1.2-alpha.20260226.1",
  "DevVersion": "9.1.2-alpha.20260226.1",
  "DirectoryPath": "sdk/storagesync/arm-storagesync",
  "ServiceDirectory": "storagesync",
  "ReadMePath": "sdk/storagesync/arm-storagesync/README.md",
  "ChangeLogPath": "sdk/storagesync/arm-storagesync/CHANGELOG.md",
  "Group": null,
  "SdkType": "mgmt",
  "IsNewSdk": true,
  "ArtifactName": "azure-arm-storagesync",
  "ReleaseStatus": "Unreleased",
  "IncludedForValidation": false,
  "AdditionalValidationPackages": null,
  "ArtifactDetails": {
    "triggeringPaths": [
      "/sdk/storagesync/ci.mgmt.yml"
    ],
    "name": "azure-arm-storagesync",
    "safeName": "azurearmstoragesync"
  },
  "CIParameters": {
    "CIMatrixConfigs": []
  },
  "SpecProjectPath": null
}
