{
  "Name": "@azure/arm-storageimportexport",
  "Version": "2.1.1-alpha.20230725.1",
  "DevVersion": "2.1.1-alpha.20230802.1",
  "DirectoryPath": "sdk/storageimportexport/arm-storageimportexport",
  "ServiceDirectory": "storageimportexport",
  "ReadMePath": "sdk/storageimportexport/arm-storageimportexport/README.md",
  "ChangeLogPath": "sdk/storageimportexport/arm-storageimportexport/CHANGELOG.md",
  "Group": null,
  "SdkType": "mgmt",
  "IsNewSdk": true,
  "ArtifactName": "azure-arm-storageimportexport",
  "ReleaseStatus": "Unreleased"
}
