{
  "Name": "@azure/arm-powerbiembedded",
  "Version": "2.0.4-alpha.20260217.1",
  "DevVersion": "2.0.4-alpha.20260217.1",
  "DirectoryPath": "sdk/powerbiembedded/arm-powerbiembedded",
  "ServiceDirectory": "powerbiembedded",
  "ReadMePath": "sdk/powerbiembedded/arm-powerbiembedded/README.md",
  "ChangeLogPath": "sdk/powerbiembedded/arm-powerbiembedded/CHANGELOG.md",
  "Group": null,
  "SdkType": "mgmt",
  "IsNewSdk": true,
  "ArtifactName": "azure-arm-powerbiembedded",
  "ReleaseStatus": "Unreleased",
  "IncludedForValidation": false,
  "AdditionalValidationPackages": null,
  "ArtifactDetails": {
    "safeName": "azurearmpowerbiembedded",
    "triggeringPaths": [
      "/sdk/powerbiembedded/ci.mgmt.yml"
    ],
    "name": "azure-arm-powerbiembedded"
  },
  "CIParameters": {
    "CIMatrixConfigs": []
  },
  "SpecProjectPath": null
}
