{
  "Name": "@azure-rest/purview-datamap",
  "Version": "1.0.0-alpha.20250102.1",
  "DevVersion": null,
  "DirectoryPath": "sdk/purview/purview-datamap-rest",
  "ServiceDirectory": "purview",
  "ReadMePath": "sdk/purview/purview-datamap-rest/README.md",
  "ChangeLogPath": "sdk/purview/purview-datamap-rest/CHANGELOG.md",
  "Group": null,
  "SdkType": "client",
  "IsNewSdk": true,
  "ArtifactName": "azure-rest-purview-datamap",
  "ReleaseStatus": null,
  "IncludedForValidation": false,
  "AdditionalValidationPackages": null,
  "ArtifactDetails": {
    "safeName": "azurerestpurviewdatamap",
    "name": "azure-rest-purview-datamap"
  },
  "CIMatrixConfigs": []
}
