{
  "Name": "@azure/arm-networkfunction",
  "Version": "3.0.0-alpha.20260626.2",
  "DevVersion": "3.0.0-alpha.20260626.2",
  "DirectoryPath": "sdk/networkfunction/arm-networkfunction",
  "ServiceDirectory": "networkfunction",
  "ReadMePath": "sdk/networkfunction/arm-networkfunction/README.md",
  "ChangeLogPath": "sdk/networkfunction/arm-networkfunction/CHANGELOG.md",
  "Group": null,
  "SdkType": "mgmt",
  "IsNewSdk": true,
  "ArtifactName": "azure-arm-networkfunction",
  "ReleaseStatus": "2026-06-26",
  "IncludedForValidation": false,
  "AdditionalValidationPackages": null,
  "ArtifactDetails": {
    "safeName": "azurearmnetworkfunction",
    "triggeringPaths": [
      "/sdk/networkfunction/ci.mgmt.yml"
    ],
    "name": "azure-arm-networkfunction"
  },
  "CIParameters": {
    "CIMatrixConfigs": []
  },
  "SpecProjectPath": "specification/networkfunction/resource-manager/Microsoft.NetworkFunction/TrafficCollector"
}
